zo/__init__.py
zomake-0.1.0.dist-info/LICENSE
zomake-0.1.0.dist-info/METADATA
zomake-0.1.0.dist-info/WHEEL
zomake-0.1.0.dist-info/top_level.txt
zomake-0.1.0.dist-info/RECORD
