Metadata-Version: 2.1
Name: zomake
Version: 0.1.0
Summary: A C/C++ build system that generates Makefiles.
Home-page: https://github.com/IY314/zomake
Author: Isaac Yee
Author-email: isaac.cl.yee@gmail.com
Classifier: Programming Language :: Python :: 3
Classifier: License :: OSI Approved :: MIT License
Classifier: Operating System :: OS Independent
Requires-Python: >=3.9
License-File: LICENSE
